django_mg/__init__.py
django_mg/__main__.py
django_mg/gui.py
django_mg/management/__init__.py
django_mg/management/commands/__init__.py
django_mg/management/commands/generate_model.py
django_mg-1.1.3.dist-info/licenses/LICENSE.txt
django_mg-1.1.3.dist-info/METADATA
django_mg-1.1.3.dist-info/WHEEL
django_mg-1.1.3.dist-info/entry_points.txt
django_mg-1.1.3.dist-info/top_level.txt
django_mg-1.1.3.dist-info/RECORD
