Metadata-Version: 2.4
Name: django-mg
Version: 1.1.3
Summary: Django Model Generator - Slash-separated fields
Author-email: Mobin Hasanghasemi <mobin.hasanghasemi.m@gmail.com>
License: MIT
Project-URL: Homepage, https://github.com/mobinhasanghasemi/django-mg
Project-URL: Repository, https://github.com/mobinhasanghasemi/django-mg.git
Project-URL: Bug Tracker, https://github.com/mobinhasanghasemi/django-mg/issues
Classifier: Development Status :: 4 - Beta
Classifier: Framework :: Django
Classifier: Framework :: Django :: 3.2
Classifier: Framework :: Django :: 4.0
Classifier: Framework :: Django :: 4.1
Classifier: Framework :: Django :: 4.2
Classifier: Intended Audience :: Developers
Classifier: License :: OSI Approved :: MIT License
Classifier: Operating System :: OS Independent
Classifier: Programming Language :: Python :: 3
Classifier: Programming Language :: Python :: 3.8
Classifier: Programming Language :: Python :: 3.9
Classifier: Programming Language :: Python :: 3.10
Classifier: Programming Language :: Python :: 3.11
Requires-Python: >=3.8
License-File: LICENSE.txt
Requires-Dist: Django>=3.2
Provides-Extra: dev
Requires-Dist: black; extra == "dev"
Requires-Dist: flake8; extra == "dev"
Requires-Dist: pytest; extra == "dev"
Requires-Dist: pytest-django; extra == "dev"
Requires-Dist: tox; extra == "dev"
Provides-Extra: filer
Requires-Dist: django-filer>=2.0; extra == "filer"
Provides-Extra: money
Requires-Dist: django-money>=3.0; extra == "money"
Provides-Extra: ckeditor
Requires-Dist: django-ckeditor>=6.0; extra == "ckeditor"
Provides-Extra: taggit
Requires-Dist: django-taggit>=3.0; extra == "taggit"
Provides-Extra: autoslug
Requires-Dist: django-autoslug>=1.9; extra == "autoslug"
Provides-Extra: gui
Requires-Dist: customtkinter>=5.2.0; extra == "gui"
Requires-Dist: tkinterdnd2>=0.4.2; extra == "gui"
Dynamic: license-file
